menglingtool_machine_learning/__init__.py
menglingtool_machine_learning/ml/__super__.py
menglingtool_machine_learning/ml/conditional.py
menglingtool_machine_learning/ml/kmeans.py
menglingtool_machine_learning/ml/knn.py
menglingtool_machine_learning/ml/lr.py
menglingtool_machine_learning/ml/mean_shift.py
menglingtool_machine_learning/ml/svc.py
menglingtool_machine_learning/nn/bp.py
menglingtool_machine_learning/nn/nn.py
menglingtool_machine_learning/nn/rbf.py
menglingtool_machine_learning/tools/data.py
menglingtool_machine_learning/tools/imgtool.py
menglingtool_machine_learning-1.0.6.dist-info/METADATA
menglingtool_machine_learning-1.0.6.dist-info/WHEEL
menglingtool_machine_learning-1.0.6.dist-info/top_level.txt
menglingtool_machine_learning-1.0.6.dist-info/RECORD
