Metadata-Version: 2.1
Name: menglingtool-machine-learning
Version: 1.0.6
Summary: 工业化! yyds
Home-page: https://www.python.org
Author: mengling
Author-email: 1321443305@qq.com
License: UNKNOWN
Platform: UNKNOWN
Requires-Python: >=3.6
Requires-Dist: numpy
Requires-Dist: torch
Requires-Dist: joblib
Requires-Dist: scikit-learn
